cph_regression/__init__.py
cph_regression/__main__.py
cph_regression/cli.py
cph_regression/regression/__init__.py
cph_regression/regression/callbacks.py
cph_regression/regression/cli.py
cph_regression/regression/datamodule.py
cph_regression/regression/dataset.py
cph_regression/regression/main.py
cph_regression/regression/mainfittest.py
cph_regression/regression/modelfactory.py
cph_regression/regression/modelmodule.py
cph_regression-0.1.0.dist-info/licenses/LICENSE
cph_regression-0.1.0.dist-info/METADATA
cph_regression-0.1.0.dist-info/WHEEL
cph_regression-0.1.0.dist-info/entry_points.txt
cph_regression-0.1.0.dist-info/top_level.txt
cph_regression-0.1.0.dist-info/RECORD
