Metadata-Version: 2.4
Name: cph-regression
Version: 0.1.0
Summary: A generic, config-driven regression training package using PyTorch Lightning
Home-page: https://github.com/imchandra11/cph-regression
Author: chandra
Author-email: chandra <chandra385123@gmail.com>
License: MIT
Project-URL: Homepage, https://github.com/imchandra11/cph-regression
Project-URL: Documentation, https://github.com/imchandra11/cph-regression
Project-URL: Repository, https://github.com/imchandra11/cph-regression
Project-URL: Issues, https://github.com/imchandra11/cph-regression/issues
Keywords: regression,machine-learning,pytorch,lightning,yaml-config
Classifier: Development Status :: 4 - Beta
Classifier: Intended Audience :: Developers
Classifier: Intended Audience :: Science/Research
Classifier: License :: OSI Approved :: MIT License
Classifier: Operating System :: OS Independent
Classifier: Programming Language :: Python :: 3
Classifier: Programming Language :: Python :: 3.8
Classifier: Programming Language :: Python :: 3.9
Classifier: Programming Language :: Python :: 3.10
Classifier: Programming Language :: Python :: 3.11
Classifier: Topic :: Scientific/Engineering :: Artificial Intelligence
Classifier: Topic :: Software Development :: Libraries :: Python Modules
Requires-Python: >=3.8
License-File: LICENSE
Requires-Dist: lightning>=2.1.0
Requires-Dist: torch>=2.0.0
Requires-Dist: torchvision>=0.15.0
Requires-Dist: Pillow>=9.0.0
Requires-Dist: pandas>=2.0.0
Requires-Dist: numpy>=1.24.0
Requires-Dist: scikit-learn>=1.3.0
Requires-Dist: joblib>=1.3.0
Requires-Dist: onnx>=1.14.0
Requires-Dist: onnxruntime<1.23.0,>=1.16.0
Requires-Dist: torchmetrics>=1.0.0
Requires-Dist: pyyaml>=6.0
Requires-Dist: fastapi>=0.104.0
Requires-Dist: uvicorn[standard]>=0.24.0
Requires-Dist: jinja2>=3.1.0
Requires-Dist: python-multipart>=0.0.6
Requires-Dist: pydantic>=2.0.0
Requires-Dist: tensorboard>=2.13.0
Requires-Dist: jsonargparse[signatures]>=4.27.7
Provides-Extra: dev
Requires-Dist: pytest>=7.0.0; extra == "dev"
Requires-Dist: pytest-cov>=4.0.0; extra == "dev"
Requires-Dist: black>=23.0.0; extra == "dev"
Requires-Dist: flake8>=6.0.0; extra == "dev"
Requires-Dist: mypy>=1.0.0; extra == "dev"
Dynamic: author
Dynamic: home-page
Dynamic: license-file
Dynamic: requires-python
